Workbook

Sheet Resumen
A1: RED DE COLEGIOS MANO AMIGA · CUMPLIMIENTO NORMATIVO
A2: DOCUMENTOS PARA CONVOCATORIAS
A3: Checklist contra el Catálogo de Cumplimiento del Sistema RCMA · 28/10/2026
A5: DOCUMENTOS QUE PIDEN | B5: EN EL SISTEMA | C5: PARCIAL | D5: NO ESTÁN | E5: COBERTURA (SÍ + ½ PARCIAL)
A6: =COUNTA(Checklist!$C$8:$C$75) | B6: =COUNTIF(Checklist!$D$8:$D$75,"Sí") | C6: =COUNTIF(Checklist!$D$8:$D$75,"Parcial") | D6: =COUNTIF(Checklist!$D$8:$D$75,"No") | E6: =IFERROR((B6+C6/2)/A6,0)
A8: AVANCE POR CATEGORÍA
A9: Categoría | B9: Documentos | C9: En el sistema | D9: Parcial | E9: No están | F9: Cobertura
A10: Documentación legal | B10: =COUNTIFS(Checklist!$B$8:$B$75,"DOCUMENTACIÓN LEGAL",Checklist!$C$8:$C$75,"<>") | C10: =COUNTIFS(Checklist!$B$8:$B$75,"DOCUMENTACIÓN LEGAL",Checklist!$D$8:$D$75,"Sí") | D10: =COUNTIFS(Checklist!$B$8:$B$75,"DOCUMENTACIÓN LEGAL",Checklist!$D$8:$D$75,"Parcial") | E10: =COUNTIFS(Checklist!$B$8:$B$75,"DOCUMENTACIÓN LEGAL",Checklist!$D$8:$D$75,"No") | F10: =IFERROR((C10+D10/2)/B10,0)
A11: Documentación fiscal | B11: =COUNTIFS(Checklist!$B$8:$B$75,"DOCUMENTACIÓN FISCAL",Checklist!$C$8:$C$75,"<>") | C11: =COUNTIFS(Checklist!$B$8:$B$75,"DOCUMENTACIÓN FISCAL",Checklist!$D$8:$D$75,"Sí") | D11: =COUNTIFS(Checklist!$B$8:$B$75,"DOCUMENTACIÓN FISCAL",Checklist!$D$8:$D$75,"Parcial") | E11: =COUNTIFS(Checklist!$B$8:$B$75,"DOCUMENTACIÓN FISCAL",Checklist!$D$8:$D$75,"No") | F11: =IFERROR((C11+D11/2)/B11,0)
A12: Documentación contable | B12: =COUNTIFS(Checklist!$B$8:$B$75,"DOCUMENTACIÓN CONTABLE",Checklist!$C$8:$C$75,"<>") | C12: =COUNTIFS(Checklist!$B$8:$B$75,"DOCUMENTACIÓN CONTABLE",Checklist!$D$8:$D$75,"Sí") | D12: =COUNTIFS(Checklist!$B$8:$B$75,"DOCUMENTACIÓN CONTABLE",Checklist!$D$8:$D$75,"Parcial") | E12: =COUNTIFS(Checklist!$B$8:$B$75,"DOCUMENTACIÓN CONTABLE",Checklist!$D$8:$D$75,"No") | F12: =IFERROR((C12+D12/2)/B12,0)
A13: Documentos del colegio | B13: =COUNTIFS(Checklist!$B$8:$B$75,"DOCUMENTOS DEL COLEGIO",Checklist!$C$8:$C$75,"<>") | C13: =COUNTIFS(Checklist!$B$8:$B$75,"DOCUMENTOS DEL COLEGIO",Checklist!$D$8:$D$75,"Sí") | D13: =COUNTIFS(Checklist!$B$8:$B$75,"DOCUMENTOS DEL COLEGIO",Checklist!$D$8:$D$75,"Parcial") | E13: =COUNTIFS(Checklist!$B$8:$B$75,"DOCUMENTOS DEL COLEGIO",Checklist!$D$8:$D$75,"No") | F13: =IFERROR((C13+D13/2)/B13,0)
A14: TOTAL | B14: =SUM(B10:B13) | C14: =SUM(C10:C13) | D14: =SUM(D10:D13) | E14: =SUM(E10:E13) | F14: =IFERROR((C14+D14/2)/B14,0)
A16: CÓMO LEERLO
A17: Sí | B17: El catálogo de Cumplimiento ya tiene un concepto que cubre el documento; se gestiona en Registro de Cumplimiento.
A18: Parcial | B18: Hay un concepto relacionado, pero no es el mismo documento o lo cubre solo en parte (ver columna "Concepto del catálogo").
A19: No | B19: No existe en el catálogo. La columna "Sugerencia" indica si conviene agregarlo a Cumplimiento o si pertenece a otra área.
A21: Fuente: "Relación Documentos para Convocatorias" (hoja Documentación) y Catálogo de Cumplimiento del Sistema RCMA (61 conceptos activos al 28/10/2026). La columna "¿En el sistema?" se puede cambiar y todo el resumen se recalcula.
A23: Colegios Mano Amiga — Juntos Transformando Vidas. | D23: Checklist Convocatorias · Cumplimiento · Sistema RCMA

Sheet Checklist
A1: RED DE COLEGIOS MANO AMIGA · CUMPLIMIENTO NORMATIVO
A2: CHECKLIST · DOCUMENTOS PARA CONVOCATORIAS
A3: ¿Lo tengo en el módulo de Cumplimiento? · Cruce documento por documento
A6: Estatus: Sí = ya está en el catálogo · Parcial = hay un concepto relacionado · No = no está. Las celdas en crema se pueden editar.
A7: No. | B7: Categoría | C7: Documento que pide la convocatoria | D7: ¿En el sistema? | E7: Concepto del catálogo de Cumplimiento | F7: Materia | G7: Periodicidad | H7: Sugerencia | I7: Observaciones
A8: DOCUMENTACIÓN LEGAL
A9: 1 | B9: DOCUMENTACIÓN LEGAL | C9: Acta constitutiva | D9: Sí | E9: #22 Acta Constitutiva de la Sociedad / Asociación | F9: Jurídico | G9: Fijo | H9: Ya está en Cumplimiento
A10: 2 | B10: DOCUMENTACIÓN LEGAL | C10: Protocolizaciones | D10: Parcial | E10: #22 Acta Constitutiva de la Sociedad / Asociación | F10: Jurídico | G10: Fijo | H10: Agregar al catálogo CN | I10: Hoy van dentro del Acta Constitutiva; cambian con cada nuevo Director o Administrador.
A11: 3 | B11: DOCUMENTACIÓN LEGAL | C11: Poder del Representante Legal | D11: Sí | E11: #26 Poder Notarial del Representante Legal | F11: Jurídico | G11: Fijo | H11: Ya está en Cumplimiento
A12: 4 | B12: DOCUMENTACIÓN LEGAL | C12: Identificación Oficial del Representante Legal | D12: Sí | E12: #25 Identificación Oficial del Representante Legal | F12: Jurídico | G12: Fijo | H12: Ya está en Cumplimiento
A13: 5 | B13: DOCUMENTACIÓN LEGAL | C13: Programa o Protocolo Interno de Protección Civil | D13: Sí | E13: #40 Programa Interno de Protección Civil (PIPC) | F13: Protección Civil | G13: Anual | H13: Ya está en Cumplimiento
A14: 6 | B14: DOCUMENTACIÓN LEGAL | C14: Constancia de Actividades Sociales (vigente) | D14: No | E14: — | G14: Fijo | H14: Agregar al catálogo CN
A15: 7 | B15: DOCUMENTACIÓN LEGAL | C15: CURP del Representante Legal | D15: No | E15: — | G15: Fijo | H15: Agregar al catálogo CN | I15: Podría ir junto con la Identificación Oficial (#25).
A16: 8 | B16: DOCUMENTACIÓN LEGAL | C16: RFC del Representante Legal | D16: No | E16: — | G16: Fijo | H16: Agregar al catálogo CN | I16: Podría ir junto con la Identificación Oficial (#25).
A17: 9 | B17: DOCUMENTACIÓN LEGAL | C17: Inscripción al Registro Público | D17: Parcial | E17: #22 Acta Constitutiva de la Sociedad / Asociación | F17: Jurídico | G17: Fijo | H17: Ya está en Cumplimiento | I17: Normalmente viene dentro del Acta Constitutiva.
A18: 10 | B18: DOCUMENTACIÓN LEGAL | C18: Número de Registro Patronal | D18: Sí | E18: #13 Registro Patronal IMSS con Grado de Riesgo | F18: Gestión de Riesgos | G18: Fijo | H18: Ya está en Cumplimiento
A19: DOCUMENTACIÓN FISCAL
A20: 1 | B20: DOCUMENTACIÓN FISCAL | C20: RI - Inscripción al SAT | D20: Parcial | E20: #7 Constancia de Situación Fiscal (RFC) | F20: Fiscal | G20: Fijo | H20: Ya está en Cumplimiento | I20: La Constancia de Situación Fiscal cubre los datos de inscripción.
A21: 2 | B21: DOCUMENTACIÓN FISCAL | C21: Cédula Fiscal (RFC del Colegio) | D21: Sí | E21: #7 Constancia de Situación Fiscal (RFC) | F21: Fiscal | G21: Fijo | H21: Ya está en Cumplimiento
A22: 3 | B22: DOCUMENTACIÓN FISCAL | C22: Constancia de Situación Fiscal (vigente) | D22: Sí | E22: #7 Constancia de Situación Fiscal (RFC) | F22: Fiscal | G22: Mensual | H22: Ya está en Cumplimiento
A23: 4 | B23: DOCUMENTACIÓN FISCAL | C23: Opinión de Cumplimiento SAT (vigente) | D23: Sí | E23: #8 Opinión de Cumplimiento de Obligaciones Fiscales (32-D) | F23: Fiscal | G23: Mensual | H23: Ya está en Cumplimiento
A24: 5 | B24: DOCUMENTACIÓN FISCAL | C24: Última publicación en el DOF, Anexo 14 (anual) | D24: No | E24: — | G24: Anual | H24: Agregar al catálogo CN | I24: Materia Donatarias.
A25: 6 | B25: DOCUMENTACIÓN FISCAL | C25: Documento de autorización de donataria expedida por el SAT/SHCP | D25: No | E25: — | G25: Fijo | H25: Agregar al catálogo CN | I25: Materia Donatarias.
A26: 7 | B26: DOCUMENTACIÓN FISCAL | C26: Carta de Donataria actualizada del SAT | D26: No | E26: — | G26: Fijo | H26: Agregar al catálogo CN | I26: Materia Donatarias.
A27: 8 | B27: DOCUMENTACIÓN FISCAL | C27: Autorización de SAT desde su origen | D27: No | E27: — | G27: Fijo | H27: Agregar al catálogo CN | I27: Materia Donatarias.
A28: 9 | B28: DOCUMENTACIÓN FISCAL | C28: Prevención de antilavado de dinero (formato y documentación del donante) | D28: Parcial | E28: #10 Aviso de Privacidad Integral (LFPDPPP) (Ley Antilavado) | F28: Fiscal / Comercial | G28: Anual | H28: Agregar al catálogo CN | I28: El concepto #10 menciona Ley Antilavado junto con Aviso de Privacidad; el formato del donante no está separado.
A29: 10 | B29: DOCUMENTACIÓN FISCAL | C29: Validación para recibir donativos del extranjero | D29: No | E29: — | G29: Fijo | H29: Agregar al catálogo CN | I29: Materia Donatarias.
A30: 11 | B30: DOCUMENTACIÓN FISCAL | C30: Carta de Acreditación de Actividades SAT (modificación de estatutos) | D30: No | E30: — | G30: Fijo | H30: Agregar al catálogo CN | I30: Materia Donatarias.
A31: DOCUMENTACIÓN CONTABLE
A32: 1 | B32: DOCUMENTACIÓN CONTABLE | C32: Carátula Bancaria (mensual) | D32: No | E32: — | G32: Mensual | H32: Fuera de CN · Contabilidad / Finanzas
A33: 2 | B33: DOCUMENTACIÓN CONTABLE | C33: Estados Financieros (año anterior) | D33: No | E33: — | G33: Anual | H33: Fuera de CN · Contabilidad / Finanzas
A34: 3 | B34: DOCUMENTACIÓN CONTABLE | C34: Declaración Anual (año anterior) | D34: No | E34: — | G34: Anual | H34: Fuera de CN · Contabilidad / Finanzas | I34: Si se quiere en CN, iría en materia Fiscal.
A35: 4 | B35: DOCUMENTACIÓN CONTABLE | C35: Balanza de comprobación (año anterior) | D35: No | E35: — | G35: Anual | H35: Fuera de CN · Contabilidad / Finanzas
A36: 5 | B36: DOCUMENTACIÓN CONTABLE | C36: Balanza General (año anterior) | D36: No | E36: — | G36: Anual | H36: Fuera de CN · Contabilidad / Finanzas
A37: 6 | B37: DOCUMENTACIÓN CONTABLE | C37: Informe de Actividades (año en curso) | D37: No | E37: — | G37: Anual | H37: Fuera de CN · Contabilidad / Finanzas
A38: 7 | B38: DOCUMENTACIÓN CONTABLE | C38: Presupuesto Anual del año en curso (ingresos - egresos) | D38: No | E38: — | G38: Anual | H38: Fuera de CN · Contabilidad / Finanzas
A39: 8 | B39: DOCUMENTACIÓN CONTABLE | C39: Último Presupuesto anual presentado a la Junta de Asistencia Privada (MA Cima, FIADES y FSA) | D39: No | E39: — | G39: Anual | H39: Fuera de CN · Contabilidad / Finanzas | I39: Solo aplica a MA Cima, FIADES y FSA.
A40: 9 | B40: DOCUMENTACIÓN CONTABLE | C40: Último Informe anual presentado a la Junta de Asistencia Privada (MA Cima, FIADES y FSA) | D40: No | E40: — | G40: Anual | H40: Fuera de CN · Contabilidad / Finanzas | I40: Solo aplica a MA Cima, FIADES y FSA.
A41: DOCUMENTOS DEL COLEGIO
A42: 1 | B42: DOCUMENTOS DEL COLEGIO | C42: Licencia de Funcionamiento | D42: Sí | E42: #17 Licencia de Funcionamiento Municipal | F42: Inmobiliaria | G42: Anual | H42: Ya está en Cumplimiento
A43: 2 | B43: DOCUMENTOS DEL COLEGIO | C43: Criterios o procedimiento para seleccionar a la población atendida (estudio socioeconómico) | D43: No | E43: — | G43: Anual | H43: Fuera de CN · institucional / Dirección
A44: 3 | B44: DOCUMENTOS DEL COLEGIO | C44: Diagrama de Teoría de Cambio del Modelo de Intervención | D44: No | E44: — | G44: Fijo | H44: Fuera de CN · Procuración / Comunicación
A45: 4 | B45: DOCUMENTOS DEL COLEGIO | C45: Currículum del Director del Colegio | D45: Parcial | E45: #61 Autorización / Nombramiento del Director | F45: Educativo | G45: Fijo | H45: Fuera de CN · institucional / Dirección | I45: El catálogo tiene la Autorización / Nombramiento del Director, no su currículum.
A46: 5 | B46: DOCUMENTOS DEL COLEGIO | C46: Organigrama general del colegio | D46: No | E46: — | G46: Fijo | H46: Fuera de CN · institucional / Dirección
A47: 6 | B47: DOCUMENTOS DEL COLEGIO | C47: Cartas de recomendación de donantes activos | D47: No | E47: — | G47: Anual | H47: Fuera de CN · Procuración / Comunicación
A48: 7 | B48: DOCUMENTOS DEL COLEGIO | C48: Presentación institucional y del colegio con proyectos validados | D48: No | E48: — | G48: Fijo | H48: Fuera de CN · Procuración / Comunicación
A49: 8 | B49: DOCUMENTOS DEL COLEGIO | C49: Informe Anual Institucional | D49: No | E49: — | G49: Anual | H49: Fuera de CN · Procuración / Comunicación
A50: 9 | B50: DOCUMENTOS DEL COLEGIO | C50: Número de docentes y administrativos por género | D50: Parcial | E50: #4 Planta Docente y Directiva (Títulos y Cédulas) | F50: Donatarias / RVOE | G50: Anual | H50: Fuera de CN · institucional / Dirección | I50: El concepto #4 pide títulos y cédulas de la planta docente, no el conteo por género.
A51: 10 | B51: DOCUMENTOS DEL COLEGIO | C51: Planeación Anual Operativa (cronograma de actividades) | D51: No | E51: — | G51: Anual | H51: Fuera de CN · institucional / Dirección
A52: 11 | B52: DOCUMENTOS DEL COLEGIO | C52: Calendario de actividades del ciclo en curso | D52: No | E52: — | G52: Anual | H52: Fuera de CN · institucional / Dirección
A53: 12 | B53: DOCUMENTOS DEL COLEGIO | C53: Mapa curricular (asignaturas por grado escolar) | D53: Parcial | E53: #5 Planes, Programas de Estudio y Horarios | F53: Donatarias / RVOE | G53: Anual | H53: Ya está en Cumplimiento | I53: Planes y Programas de Estudio (#5) lo cubre en buena parte.
A54: 13 | B54: DOCUMENTOS DEL COLEGIO | C54: Reglamento Interno | D54: Sí | E54: #6 Reglamento Escolar Interno | F54: Donatarias / RVOE | G54: Fijo | H54: Ya está en Cumplimiento
A55: 14 | B55: DOCUMENTOS DEL COLEGIO | C55: Aviso de Privacidad | D55: Sí | E55: #10 Aviso de Privacidad Integral (LFPDPPP) (Ley Antilavado) | F55: Fiscal / Comercial | G55: Fijo | H55: Ya está en Cumplimiento
A56: 15 | B56: DOCUMENTOS DEL COLEGIO | C56: Video institucional actualizado | D56: No | E56: — | G56: Anual | H56: Fuera de CN · Procuración / Comunicación
A57: 16 | B57: DOCUMENTOS DEL COLEGIO | C57: Logotipo del colegio | D57: No | E57: — | G57: Fijo | H57: Fuera de CN · Procuración / Comunicación
A58: 17 | B58: DOCUMENTOS DEL COLEGIO | C58: Fotos (instalaciones y alumnado) | D58: No | E58: — | G58: Mensual | H58: Fuera de CN · Procuración / Comunicación
A59: 18 | B59: DOCUMENTOS DEL COLEGIO | C59: Premios y reconocimientos nacionales y estatales | D59: No | E59: — | G59: Mensual | H59: Fuera de CN · Procuración / Comunicación
A60: 19 | B60: DOCUMENTOS DEL COLEGIO | C60: Manual de Identidad | D60: No | E60: — | G60: Fijo | H60: Fuera de CN · Procuración / Comunicación
A61: 20 | B61: DOCUMENTOS DEL COLEGIO | C61: Costo de colegiatura por sección | D61: No | E61: — | G61: Anual | H61: Fuera de CN · institucional / Dirección
A62: 21 | B62: DOCUMENTOS DEL COLEGIO | C62: Comprobante de domicilio (vigente) | D62: Sí | E62: #16 Comprobante de Domicilio (CFE o Agua) | F62: Inmobiliaria | G62: Bimestral | H62: Ya está en Cumplimiento | I62: Debe coincidir con el domicilio de la Constancia de Situación Fiscal.
A63: 22 | B63: DOCUMENTOS DEL COLEGIO | C63: Estadísticas de alumnado (egresados del último grado) | D63: No | E63: — | G63: Anual | H63: Fuera de CN · institucional / Dirección
A64: 23 | B64: DOCUMENTOS DEL COLEGIO | C64: Medición de impacto | D64: No | E64: — | G64: Anual | H64: Fuera de CN · Procuración / Comunicación
A65: 24 | B65: DOCUMENTOS DEL COLEGIO | C65: Código de Ética y Conducta | D65: No | E65: — | G65: Anual | H65: Agregar al catálogo CN | I65: Materia Jurídico.
A66: 25 | B66: DOCUMENTOS DEL COLEGIO | C66: Predial | D66: Sí | E66: #18 Boleta Predial Vigente | F66: Inmobiliaria | G66: Anual | H66: Ya está en Cumplimiento
A67: 26 | B67: DOCUMENTOS DEL COLEGIO | C67: Uso de suelo | D67: Sí | E67: #19 Dictamen / Licencia de Uso de Suelo Educativo | F67: Inmobiliaria | G67: Anual | H67: Ya está en Cumplimiento
A68: 27 | B68: DOCUMENTOS DEL COLEGIO | C68: Protección Civil | D68: Sí | E68: #40 Programa Interno de Protección Civil (PIPC) · #43 Visto Bueno de Programa de Protección Civil (Municipal o Estatal) | F68: Protección Civil | G68: Anual | H68: Ya está en Cumplimiento | I68: PIPC (#40) y Visto Bueno de PC (#43).
A69: 28 | B69: DOCUMENTOS DEL COLEGIO | C69: RVOEs (todas las secciones del colegio) | D69: Sí | E69: #1 Acuerdo de Incorporación RVOE Iniciales · #3 Refrendo de Incorporación de RVOE | F69: Donatarias / RVOE | G69: Fijo | H69: Ya está en Cumplimiento | I69: Acuerdo RVOE (#1) y su refrendo anual (#3).
A70: 29 | B70: DOCUMENTOS DEL COLEGIO | C70: Documentos de convenios (empresas o universidades) | D70: Parcial | E70: #2 Convenio de Apoyo Económico | F70: Donatarias / RVOE | G70: Anual | H70: Agregar al catálogo CN | I70: El #2 es Convenio de Apoyo Económico; los convenios con empresas o universidades no están.
A71: 30 | B71: DOCUMENTOS DEL COLEGIO | C71: Programas del colegio (SEP y modelo educativo) | D71: Sí | E71: #5 Planes, Programas de Estudio y Horarios | F71: Donatarias / RVOE | G71: Fijo | H71: Ya está en Cumplimiento
A72: 31 | B72: DOCUMENTOS DEL COLEGIO | C72: Contrato de Comodato (si aplica) | D72: Sí | E72: #23 Contrato de Comodato o Arrendamiento | F72: Jurídico | G72: Fijo | H72: Ya está en Cumplimiento
A73: 32 | B73: DOCUMENTOS DEL COLEGIO | C73: Cartas de agradecimiento a donantes nuevos e históricos | D73: No | E73: — | G73: Anual | H73: Fuera de CN · Procuración / Comunicación
A74: 33 | B74: DOCUMENTOS DEL COLEGIO | C74: Atribuciones y obligaciones del Patronato (FIADES, MA Cima, FSA) | D74: No | E74: — | G74: Fijo | H74: Fuera de CN · institucional / Dirección | I74: Solo donde hay Patronato.
A75: 34 | B75: DOCUMENTOS DEL COLEGIO | C75: Actas o minutas de las últimas 3 sesiones del Patronato | D75: No | E75: — | G75: Bimestral | H75: Fuera de CN · institucional / Dirección | I75: Solo donde hay Patronato.
A77: Colegios Mano Amiga — Juntos Transformando Vidas. | F77: Checklist Convocatorias · Cumplimiento · Sistema RCMA

Sheet Catálogo CN
A1: RED DE COLEGIOS MANO AMIGA · CUMPLIMIENTO NORMATIVO
A2: CATÁLOGO DE CUMPLIMIENTO
A3: Conceptos activos en el Sistema RCMA (61) · ¿cuáles pide la convocatoria?
A6: # | B6: Concepto | C6: Materia | D6: Periodicidad | E6: ¿Lo pide la convocatoria? | F6: Documento de la convocatoria
A7: 1 | B7: Acuerdo de Incorporación RVOE Iniciales | C7: Donatarias / RVOE | D7: Único trámite | E7: Sí | F7: RVOEs (todas las secciones del colegio)
A8: 2 | B8: Convenio de Apoyo Económico | C8: Donatarias / RVOE | D8: Anual | E8: Sí | F8: Documentos de convenios (empresas o universidades)
A9: 3 | B9: Refrendo de Incorporación de RVOE | C9: Donatarias / RVOE | D9: Anual | E9: Sí | F9: RVOEs (todas las secciones del colegio)
A10: 4 | B10: Planta Docente y Directiva (Títulos y Cédulas) | C10: Donatarias / RVOE | D10: Anual | E10: Sí | F10: Número de docentes y administrativos por género
A11: 5 | B11: Planes, Programas de Estudio y Horarios | C11: Donatarias / RVOE | D11: Anual | E11: Sí | F11: Mapa curricular (asignaturas por grado escolar) · Programas del colegio (SEP y modelo educativo)
A12: 6 | B12: Reglamento Escolar Interno | C12: Donatarias / RVOE | D12: Anual | E12: Sí | F12: Reglamento Interno
A13: 7 | B13: Constancia de Situación Fiscal (RFC) | C13: Fiscal | D13: Trimestral | E13: Sí | F13: RI - Inscripción al SAT · Cédula Fiscal (RFC del Colegio) · Constancia de Situación Fiscal (vigente)
A14: 8 | B14: Opinión de Cumplimiento de Obligaciones Fiscales (32-D) | C14: Fiscal | D14: Mensual | E14: Sí | F14: Opinión de Cumplimiento SAT (vigente)
A15: 9 | B15: Contrato de Adhesión (PROFECO) | C15: Fiscal / Comercial | D15: Único trámite | E15: No
A16: 10 | B16: Aviso de Privacidad Integral (LFPDPPP) (Ley Antilavado) | C16: Fiscal / Comercial | D16: Único trámite | E16: Sí | F16: Prevención de antilavado de dinero (formato y documentación del donante) · Aviso de Privacidad
A17: 12 | B17: Póliza de Seguro Escolar (Alumnos) | C17: Gestión de Riesgos | D17: Anual | E17: No
A18: 13 | B18: Registro Patronal IMSS con Grado de Riesgo | C18: Gestión de Riesgos | D18: Único trámite | E18: Sí | F18: Número de Registro Patronal
A19: 14 | B19: Seguro de Inmuebles y Contenidos | C19: Gestión de Riesgos | D19: Anual | E19: No
A20: 15 | B20: Seguro de Responsabilidad Civil Generación/Terceros | C20: Gestión de Riesgos | D20: Anual | E20: No
A21: 16 | B21: Comprobante de Domicilio (CFE o Agua) | C21: Inmobiliaria | D21: Mensual | E21: Sí | F21: Comprobante de domicilio (vigente)
A22: 17 | B22: Licencia de Funcionamiento Municipal | C22: Inmobiliaria | D22: Anual | E22: Sí | F22: Licencia de Funcionamiento
A23: 18 | B23: Boleta Predial Vigente | C23: Inmobiliaria | D23: Anual | E23: Sí | F23: Predial
A24: 19 | B24: Dictamen / Licencia de Uso de Suelo Educativo | C24: Inmobiliaria | D24: Único trámite | E24: Sí | F24: Uso de suelo
A25: 20 | B25: Licencia de Anuncios y Publicidad Exterior | C25: Inmobiliaria | D25: Anual | E25: No
A26: 21 | B26: Evaluación de Impacto Estatal (COIME) | C26: Inmobiliaria | D26: Único trámite | E26: No
A27: 22 | B27: Acta Constitutiva de la Sociedad / Asociación | C27: Jurídico | D27: Único trámite | E27: Sí | F27: Acta constitutiva · Protocolizaciones · Inscripción al Registro Público
A28: 23 | B28: Contrato de Comodato o Arrendamiento | C28: Jurídico | D28: Único trámite | E28: Sí | F28: Contrato de Comodato (si aplica)
A29: 24 | B29: Escrituras del Inmueble | C29: Jurídico | D29: Único trámite | E29: No
A30: 25 | B30: Identificación Oficial del Representante Legal | C30: Jurídico | D30: Cada 10 años | E30: Sí | F30: Identificación Oficial del Representante Legal
A31: 26 | B31: Poder Notarial del Representante Legal | C31: Jurídico | D31: Único trámite | E31: Sí | F31: Poder del Representante Legal
A32: 27 | B32: Reglamento Interior de Trabajo Depositado | C32: Jurídico | D32: Único trámite | E32: No
A33: 28 | B33: Constancia de Seguridad Estructural (DRO) | C33: Construcción | D33: Anual | E33: No
A34: 29 | B34: Memoria de Cálculo y Planos As-Built | C34: Construcción | D34: Único trámite | E34: No
A35: 30 | B35: Comité Interno de Protección Civil | C35: Protección Civil | D35: Anual | E35: No
A36: 31 | B36: Cronograma de Mantenimiento en Instalaciones | C36: Protección Civil | D36: Anual | E36: No
A37: 32 | B37: Diagrama Unifilar de Instalaciones Eléctricas | C37: Protección Civil | D37: Anual | E37: No
A38: 33 | B38: Dictamen de Gas (LP / Natural) | C38: Protección Civil | D38: Anual | E38: No
A39: 34 | B39: Dictamen Eléctrico (UVIE) | C39: Protección Civil | D39: Anual | E39: No
A40: 35 | B40: Plan de Continuidad de Operaciones | C40: Protección Civil | D40: Anual | E40: No
A41: 36 | B41: Plano: Accesibilidad para Personas con Discapacidad | C41: Protección Civil | D41: Anual | E41: No
A42: 37 | B42: Plano: Cajones de Estacionamiento y Ascenso/Descenso | C42: Protección Civil | D42: Anual | E42: No
A43: 38 | B43: Plano: Rutas de Evacuación y Equipos de Emergencia | C43: Protección Civil | D43: Anual | E43: No
A44: 39 | B44: Plano: Ubicación de Botiquines de Primeros Auxilios | C44: Protección Civil | D44: Anual | E44: No
A45: 40 | B45: Programa Interno de Protección Civil (PIPC) | C45: Protección Civil | D45: Anual | E45: Sí | F45: Programa o Protocolo Interno de Protección Civil · Protección Civil
A46: 41 | B46: Registro de Constancia Estructural | C46: Protección Civil | D46: Anual | E46: No
A47: 42 | B47: Sistema de Alerta Sísmica (Bitacora de Pruebas y Mantenimiento) | C47: Protección Civil | D47: Anual | E47: No
A48: 43 | B48: Visto Bueno de Programa de Protección Civil (Municipal o Estatal) | C48: Protección Civil | D48: Anual | E48: Sí | F48: Protección Civil
A49: 44 | B49: Visto Bueno de Seguridad y Operación (Visto Bueno de Bomberos) | C49: Protección Civil | D49: Anual | E49: No
A50: 45 | B50: Registro del Consultor / Tercer Acreditado | C50: Protección Civil | D50: Anual | E50: No
A51: 46 | B51: Constancias de Capacitación de Brigadistas (DC-3) | C51: Protección Civil | D51: Anual | E51: No
A52: 47 | B52: Calendario y Bitácora de Simulacros | C52: Protección Civil | D52: Anual | E52: No
A53: 48 | B53: Carta Responsiva y Mantenimiento de Extintores | C53: Protección Civil | D53: Anual | E53: No
A54: 49 | B54: Señalética Oficial Instalada (Bitacora e Inventario) | C54: Protección Civil | D54: Anual | E54: No
A55: 50 | B55: Detectores de Humo y Alarma Contraincendios (Bitacora e Inventario) | C55: Protección Civil | D55: Anual | E55: No
A56: 51 | B56: Lámparas de Iluminación de Emergencia (Bitacora e Inventario) | C56: Protección Civil | D56: Anual | E56: No
A57: 52 | B57: Botiquines e Insumos Médicos Equipados (Bitacora e Inventario) | C57: Protección Civil | D57: Anual | E57: No
A58: 53 | B58: Bitácora de Mantenimiento a Subestación / Planta | C58: Protección Civil | D58: Anual | E58: No
A59: 55 | B59: Certificado de Fumigación y Control de Plagas | C59: Salud y Sanidad | D59: Trimestral | E59: No
A60: 56 | B60: Licencia / Aviso Sanitario para Cafetería / Comedor | C60: Salud y Sanidad | D60: Único trámite | E60: No
... A64: 60 | B64: Autorización de la Denominación del Plantel | C64: Educativo | D64: Único trámite | E64: No
A65: 61 | B65: Autorización / Nombramiento del Director | C65: Educativo | D65: Único trámite | E65: Sí | F65: Currículum del Director del Colegio
A66: 62 | B66: Clave de Centro de Trabajo (CCT) | C66: Educativo | D66: Único trámite | E66: No
A67: 63 | B67: Acervo Bibliográfico Mínimo | C67: Educativo | D67: Único trámite | E67: No
A69: Colegios Mano Amiga — Juntos Transformando Vidas. | E69: Checklist Convocatorias · Cumplimiento · Sistema RCMA
